{
  "project_info": {
    "project_number": "805447542650",
    "project_id": "learnify2-8c557",
    "storage_bucket": "learnify2-8c557.firebasestorage.app"
  },
  "client": [
    {
      "client_info": {
        "mobilesdk_app_id": "1:805447542650:android:8b0edfa2c36845896e18c3",
        "android_client_info": {
          "package_name": "com.example.learnify"
        }
      },
      "oauth_client": [],
      "api_key": [
        {
          "current_key": "AIzaSyASFcnMByeDV7KrkAUjgUElUE-fo9-8f3k"
        }
      ],
      "services": {
        "appinvite_service": {
          "other_platform_oauth_client": []
        }
      }
    }
  ],
  "configuration_version": "1"
}